sympy2c/__init__.py
sympy2c/build_f2c.py
sympy2c/build_gsl.py
sympy2c/build_lsoda.py
sympy2c/build_lsoda_fast.py
sympy2c/compiler.py
sympy2c/create_curry_class.py
sympy2c/expressions.py
sympy2c/function.py
sympy2c/globals.py
sympy2c/integral.py
sympy2c/interpolation.py
sympy2c/lu_generator.py
sympy2c/module.py
sympy2c/ode.py
sympy2c/ode_combined.py
sympy2c/ode_combined_cython_template.pyx
sympy2c/ode_fast.py
sympy2c/ode_fast_cython_template.pyx
sympy2c/python_function.py
sympy2c/rec_inv.py
sympy2c/speedup.py
sympy2c/symbol.py
sympy2c/utils.py
sympy2c/vector.py
sympy2c/visitor.py
sympy2c/wrapper.py
sympy2c/c_code/__init__.py
sympy2c/c_code/lsoda.c
sympy2c/f2c_files/abort_.c
sympy2c/f2c_files/arith.h
sympy2c/f2c_files/backspac.c
sympy2c/f2c_files/c_abs.c
sympy2c/f2c_files/c_cos.c
sympy2c/f2c_files/c_div.c
sympy2c/f2c_files/c_exp.c
sympy2c/f2c_files/c_log.c
sympy2c/f2c_files/c_sin.c
sympy2c/f2c_files/c_sqrt.c
sympy2c/f2c_files/cabs.c
sympy2c/f2c_files/close.c
sympy2c/f2c_files/ctype.c
sympy2c/f2c_files/d_abs.c
sympy2c/f2c_files/d_acos.c
sympy2c/f2c_files/d_asin.c
sympy2c/f2c_files/d_atan.c
sympy2c/f2c_files/d_atn2.c
sympy2c/f2c_files/d_cnjg.c
sympy2c/f2c_files/d_cos.c
sympy2c/f2c_files/d_cosh.c
sympy2c/f2c_files/d_dim.c
sympy2c/f2c_files/d_exp.c
sympy2c/f2c_files/d_imag.c
sympy2c/f2c_files/d_int.c
sympy2c/f2c_files/d_lg10.c
sympy2c/f2c_files/d_log.c
sympy2c/f2c_files/d_mod.c
sympy2c/f2c_files/d_nint.c
sympy2c/f2c_files/d_prod.c
sympy2c/f2c_files/d_sign.c
sympy2c/f2c_files/d_sin.c
sympy2c/f2c_files/d_sinh.c
sympy2c/f2c_files/d_sqrt.c
sympy2c/f2c_files/d_tan.c
sympy2c/f2c_files/d_tanh.c
sympy2c/f2c_files/derf_.c
sympy2c/f2c_files/derfc_.c
sympy2c/f2c_files/dfe.c
sympy2c/f2c_files/dolio.c
sympy2c/f2c_files/dtime_.c
sympy2c/f2c_files/due.c
sympy2c/f2c_files/ef1asc_.c
sympy2c/f2c_files/ef1cmc_.c
sympy2c/f2c_files/endfile.c
sympy2c/f2c_files/erf_.c
sympy2c/f2c_files/erfc_.c
sympy2c/f2c_files/err.c
sympy2c/f2c_files/etime_.c
sympy2c/f2c_files/exit_.c
sympy2c/f2c_files/f2c.h
sympy2c-2.3.1.dist-info/licenses/AUTHORS.rst
sympy2c-2.3.1.dist-info/licenses/LICENSE.rst
sympy2c-2.3.1.dist-info/METADATA
sympy2c-2.3.1.dist-info/WHEEL
sympy2c-2.3.1.dist-info/top_level.txt
sympy2c-2.3.1.dist-info/RECORD
